ftlangdetect/__init__.py
ftlangdetect/detect.py
tests/__init__.py
tests/test_detect.py
fasttext_langdetect_wheel-1.0.5.dist-info/LICENSE
fasttext_langdetect_wheel-1.0.5.dist-info/METADATA
fasttext_langdetect_wheel-1.0.5.dist-info/WHEEL
fasttext_langdetect_wheel-1.0.5.dist-info/top_level.txt
fasttext_langdetect_wheel-1.0.5.dist-info/RECORD
