Metadata-Version: 2.1
Name: fasttext-langdetect-wheel
Version: 1.0.5
Summary: 80x faster and 95% accurate language identification with Fasttext
Home-page: https://github.com/zafercavdar/fasttext-langdetect.git
Download-URL: https://github.com/zafercavdar/fasttext-langdetect/archive/refs/tags/v1.0.5.tar.gz
Author: Zafer Cavdar
Author-email: zafercavdar@yahoo.com
License: MIT
Keywords: fasttext,langdetect,language detection,language identification
Classifier: Development Status :: 5 - Production/Stable
Classifier: Intended Audience :: Developers
Classifier: Topic :: Scientific/Engineering :: Artificial Intelligence
Classifier: Topic :: Scientific/Engineering :: Information Analysis
Classifier: License :: OSI Approved :: MIT License
Classifier: Programming Language :: Python :: 3
Classifier: Programming Language :: Python :: 3.5
Classifier: Programming Language :: Python :: 3.6
Classifier: Programming Language :: Python :: 3.7
Classifier: Programming Language :: Python :: 3.8
Classifier: Programming Language :: Python :: 3.9
Classifier: Programming Language :: Python :: 3.10
Classifier: Programming Language :: Python :: 3.11
License-File: LICENSE
Requires-Dist: fasttext-wheel (>=0.9.1)
Requires-Dist: requests (>=2.22.0)
